MANIFEST.in
README.rst
setup.cfg
setup.py
tw2/__init__.py
tw2.jqplugins.fancytree.egg-info/PKG-INFO
tw2.jqplugins.fancytree.egg-info/SOURCES.txt
tw2.jqplugins.fancytree.egg-info/dependency_links.txt
tw2.jqplugins.fancytree.egg-info/entry_points.txt
tw2.jqplugins.fancytree.egg-info/namespace_packages.txt
tw2.jqplugins.fancytree.egg-info/not-zip-safe
tw2.jqplugins.fancytree.egg-info/requires.txt
tw2.jqplugins.fancytree.egg-info/top_level.txt
tw2/jqplugins/__init__.py
tw2/jqplugins/fancytree/__init__.py
tw2/jqplugins/fancytree/base.py
tw2/jqplugins/fancytree/defaults.py
tw2/jqplugins/fancytree/extensions.py
tw2/jqplugins/fancytree/samples.py
tw2/jqplugins/fancytree/widgets.py
tw2/jqplugins/fancytree/static/jquery/plugins/fancytree/2.3.0/MIT-LICENSE.txt
tw2/jqplugins/fancytree/static/jquery/plugins/fancytree/2.3.0/jquery.fancytree-all.js
tw2/jqplugins/fancytree/static/jquery/plugins/fancytree/2.3.0/jquery.fancytree-custom.min.js
tw2/jqplugins/fancytree/static/jquery/plugins/fancytree/2.3.0/jquery.fancytree.js
tw2/jqplugins/fancytree/static/jquery/plugins/fancytree/2.3.0/jquery.fancytree.min.js
tw2/jqplugins/fancytree/static/jquery/plugins/fancytree/2.3.0/skin-awesome/ui.fancytree.css
tw2/jqplugins/fancytree/static/jquery/plugins/fancytree/2.3.0/skin-awesome/ui.fancytree.min.css
tw2/jqplugins/fancytree/static/jquery/plugins/fancytree/2.3.0/skin-bootstrap/jquery.fancytree.css
tw2/jqplugins/fancytree/static/jquery/plugins/fancytree/2.3.0/skin-bootstrap/ui.fancytree.css
tw2/jqplugins/fancytree/static/jquery/plugins/fancytree/2.3.0/skin-bootstrap/ui.fancytree.min.css
tw2/jqplugins/fancytree/static/jquery/plugins/fancytree/2.3.0/skin-lion/icons.gif
tw2/jqplugins/fancytree/static/jquery/plugins/fancytree/2.3.0/skin-lion/loading.gif
tw2/jqplugins/fancytree/static/jquery/plugins/fancytree/2.3.0/skin-lion/ui.fancytree.css
tw2/jqplugins/fancytree/static/jquery/plugins/fancytree/2.3.0/skin-lion/ui.fancytree.min.css
tw2/jqplugins/fancytree/static/jquery/plugins/fancytree/2.3.0/skin-themeroller/icons.gif
tw2/jqplugins/fancytree/static/jquery/plugins/fancytree/2.3.0/skin-themeroller/loading.gif
tw2/jqplugins/fancytree/static/jquery/plugins/fancytree/2.3.0/skin-themeroller/ui.fancytree.css
tw2/jqplugins/fancytree/static/jquery/plugins/fancytree/2.3.0/skin-themeroller/ui.fancytree.min.css
