Metadata-Version: 1.1
Name: tw2.jqplugins.fancytree
Version: 0.0.2
Summary: toscawidgets2 wrapper for the fancytree jQuery plugin
Home-page: http://github.com/toscawidgets/tw2.jqplugins.fancytree
Author: Robert Sudwarts
Author-email: robert.sudwarts@gmail.com
License: MIT
Keywords: toscawidgets.widgets
Platform: UNKNOWN
Classifier: Development Status :: 3 - Alpha
Classifier: Environment :: Web Environment
Classifier: Environment :: Web Environment :: ToscaWidgets
Classifier: Topic :: Software Development :: Libraries :: Python Modules
Classifier: Topic :: Software Development :: Widget Sets
Classifier: Intended Audience :: Developers
Classifier: Operating System :: OS Independent
Classifier: Programming Language :: Python
